dbcan/CGCFinder_pandas_class.py
dbcan/OverviewGenerator.py
dbcan/__init__.py
dbcan/cgc_substrate_prediction.py
dbcan/dbCAN_database.py
dbcan/diamond.py
dbcan/generate_cgc_gff.py
dbcan/input_process.py
dbcan/process_dbcan_sub.py
dbcan/pyhmmer_search.py
dbcan/run_dbcan.py
dbcan/syntenic_plot.py
dbcan/utils/__init__.py
dbcan/utils/diamond_unassembly.py
dbcan/utils/plots.py
dbcan/utils/utils.py
run_dbcan_new-5.0.5.dist-info/METADATA
run_dbcan_new-5.0.5.dist-info/WHEEL
run_dbcan_new-5.0.5.dist-info/entry_points.txt
run_dbcan_new-5.0.5.dist-info/top_level.txt
run_dbcan_new-5.0.5.dist-info/RECORD
